LICENSE
MANIFEST.in
README.md
setup.py
custom_app/__init__.py
custom_app/models.py
custom_app/graphql/__init__.py
custom_app/graphql/schema.py
custom_app/migrations/0001_initial.py
custom_app/migrations/__init__.py
djraphql/__init__.py
djraphql/access_permissions.py
djraphql/django_models.py
djraphql/entities.py
djraphql/fields.py
djraphql/filters.py
djraphql/schema_builder.py
djraphql/type_registry.py
djraphql.egg-info/PKG-INFO
djraphql.egg-info/SOURCES.txt
djraphql.egg-info/dependency_links.txt
djraphql.egg-info/requires.txt
djraphql.egg-info/top_level.txt
djraphql/schemas/__init__.py
djraphql/schemas/abstract_type_builder.py
djraphql/schemas/default/__init__.py
djraphql/schemas/default/mappings.py
djraphql/schemas/default/resolvers/__init__.py
djraphql/schemas/default/resolvers/aggregate.py
djraphql/schemas/default/resolvers/by_pk.py
djraphql/schemas/default/resolvers/delete.py
djraphql/schemas/default/resolvers/field.py
djraphql/schemas/default/resolvers/group_by.py
djraphql/schemas/default/resolvers/insert.py
djraphql/schemas/default/resolvers/list.py
djraphql/schemas/default/resolvers/update.py
djraphql/schemas/default/types/__init__.py
djraphql/schemas/default/types/mutations/__init__.py
djraphql/schemas/default/types/mutations/delete.py
djraphql/schemas/default/types/mutations/insert.py
djraphql/schemas/default/types/mutations/update.py
djraphql/schemas/default/types/queries/__init__.py
djraphql/schemas/default/types/queries/aggregate.py
djraphql/schemas/default/types/queries/by_pk.py
djraphql/schemas/default/types/queries/many.py
djraphql/schemas/default/types/shared/__init__.py
djraphql/schemas/default/types/shared/aggregate_basic.py
djraphql/schemas/default/types/shared/aggregate_group_by.py
djraphql/schemas/default/types/shared/aggregate_result.py
djraphql/schemas/default/types/shared/basic.py
djraphql/schemas/default/types/shared/enum.py
djraphql/schemas/default/types/shared/insert_input_type.py
djraphql/schemas/default/types/shared/list_update_input_type.py
djraphql/schemas/default/types/shared/nested_item_insert_input_type.py
djraphql/schemas/default/types/shared/nested_item_update_input_type.py
