Metadata-Version: 2.1
Name: djraphql
Version: 0.2.17
Summary: DjraphQL builds a flexible & performant GraphQL schema by examining your Django models.
Home-page: https://github.com/Radico/djraphql
Author: Joel Gardner
Author-email: joel@simondata.com
Classifier: Programming Language :: Python
Classifier: Operating System :: OS Independent
Requires-Python: >=3.7
License-File: LICENSE
Requires-Dist: django
Requires-Dist: graphene
Requires-Dist: six
